guibbon/__init__.py
guibbon/colors.py
guibbon/image_viewer.py
guibbon/keyboard_event_handler.py
guibbon/mouse_pan.py
guibbon/transform_matrix.py
guibbon/typedef.py
guibbon/wrapped_tk_widgets.py
guibbon/icons/icon32.png
guibbon/interactive_overlays/__init__.py
guibbon/interactive_overlays/base.py
guibbon/interactive_overlays/multi_slider.py
guibbon/interactive_overlays/polygons.py
guibbon/widgets/button_widget.py
guibbon/widgets/check_button_list_widget.py
guibbon/widgets/check_button_widget.py
guibbon/widgets/color_picker_widget.py
guibbon/widgets/color_space_widget.py
guibbon/widgets/multi_slider_widget.py
guibbon/widgets/radio_buttons_widget.py
guibbon/widgets/slider_widget.py
guibbon/widgets/treeview_widget.py
guibbon/widgets/widget.py
guibbon-0.4.0.dist-info/METADATA
guibbon-0.4.0.dist-info/WHEEL
guibbon-0.4.0.dist-info/licenses/LICENSE
guibbon-0.4.0.dist-info/RECORD
