Metadata-Version: 2.4
Name: guibbon
Version: 0.4.0
Summary: Very high level GUI with an API similar to the HighGUI of OpenCV
Project-URL: repository, https://github.com/ManuGira/Guibbon.git
Author-email: Manu Gira <manu.gira@outlook.com>
License-File: LICENSE
Requires-Python: >=3.10
Requires-Dist: opencv-python>=4.12.0.88
Requires-Dist: pillow>=12.0.0
